{"success":true,"parcel":{"id":1964,"height":8,"token":null,"name":null,"traffic_visits":1087,"address":"21 Junior Walk","visible":true,"geometry":{"type":"Polygon","crs":{"type":"name","properties":{"name":"EPSG:3857"}},"coordinates":[[[-3.73,2.3],[-3.73,2.5],[-3.6,2.5],[-3.6,2.3],[-3.73,2.3]]]},"area":259.99999999999943,"streets":[{"name":"Junior Walk","geometry":{"type":"LineString","crs":{"type":"name","properties":{"name":"EPSG:3857"}},"coordinates":[[-3.75,1.89],[-3.75,3.46]]},"visible":true,"kind":"road","island":"Origin City","id":12},{"name":"Frances Pass","geometry":{"type":"LineString","crs":{"type":"name","properties":{"name":"EPSG:3857"}},"coordinates":[[-3.75,2.28],[-3.16,2.28]]},"visible":true,"kind":"road","island":"Origin City","id":334},{"name":"Requiem Garden","geometry":{"type":"LineString","crs":{"type":"name","properties":{"name":"EPSG:3857"}},"coordinates":[[-4.82,2.49],[-3.75,2.49]]},"visible":true,"kind":"road","island":"Origin City","id":542},{"name":"Tron Alley","geometry":{"type":"LineString","crs":{"type":"name","properties":{"name":"EPSG:3857"}},"coordinates":[[-3.58,2.28],[-3.58,2.62]]},"visible":true,"kind":"road","island":"Origin City","id":577}],"distance_to_center":427.2,"distance_to_closest_common":336.27,"distance_to_ocean":108,"x1":-373,"x2":-360,"y1":0,"y2":8,"z1":230,"z2":250,"suburb":"Memes","is_common":false,"owner":"0x48778011be66236f8e7fb9933496167852004668","owner_name":null,"updated_at":"2020-08-18T12:15:05.298Z","parcel_users":null,"label":null,"description":null,"lightmap_status":"None","content":null,"settings":{"sandbox":false,"hosted_scripts":false},"island":"Origin City","kind":"plot","minted":true}}