{"success":true,"parcel":{"id":4539,"height":14,"token":null,"name":null,"traffic_visits":7043,"address":"11 Rāwhitiroa","visible":true,"geometry":{"type":"Polygon","crs":{"type":"name","properties":{"name":"EPSG:3857"}},"coordinates":[[[6.96,-6.56],[6.96,-6.67],[6.740100005,-6.67],[6.740100005,-6.56],[6.96,-6.56]]]},"area":241.88999455609644,"streets":[{"name":"Rāwhitiroa","geometry":{"type":"LineString","crs":{"type":"name","properties":{"name":"EPSG:3857"}},"coordinates":[[6.98,-7.720000000000001],[6.98,-6.24]]},"visible":true,"kind":null,"island":"Poneke","id":1921},{"name":"Ōpuke","geometry":{"type":"LineString","crs":{"type":"name","properties":{"name":"EPSG:3857"}},"coordinates":[[6.61,-6.69],[6.98,-6.69]]},"visible":true,"kind":null,"island":"Poneke","id":1939},{"name":"Kairara","geometry":{"type":"LineString","crs":{"type":"name","properties":{"name":"EPSG:3857"}},"coordinates":[[6.98,-6.61],[7.35,-6.61]]},"visible":true,"kind":null,"island":"Poneke","id":1944},{"name":"Awahōu","geometry":{"type":"LineString","crs":{"type":"name","properties":{"name":"EPSG:3857"}},"coordinates":[[6.61,-6.54],[6.98,-6.54]]},"visible":true,"kind":null,"island":"Poneke","id":1946},{"name":"Tironui","geometry":{"type":"LineString","crs":{"type":"name","properties":{"name":"EPSG:3857"}},"coordinates":[[6.800000000000001,-6.54],[6.800000000000001,-6.24]]},"visible":true,"kind":null,"island":"Poneke","id":1950},{"name":"Waihīnau","geometry":{"type":"LineString","crs":{"type":"name","properties":{"name":"EPSG:3857"}},"coordinates":[[6.73,-6.98],[6.73,-6.69]]},"visible":true,"kind":null,"island":"Poneke","id":1951}],"distance_to_center":940.55,"distance_to_closest_common":230.22,"distance_to_ocean":34,"x1":674,"x2":696,"y1":0,"y2":14,"z1":-667,"z2":-656,"suburb":"Poneke","is_common":false,"owner":"0xf7425fb026f9297fcc57b14ace187215442586a2","owner_name":null,"updated_at":"2021-04-16T23:02:41.011Z","parcel_users":null,"label":null,"description":null,"lightmap_status":"None","content":{"features":[{"url":"","type":"megavox","uuid":"55ec170d-02ba-45e4-b984-72ce786e289b","flipX":true,"scale":[0.5,0.5,0.5],"version":"5.51.4","position":[3,0.75,1.75],"rotation":[0,1.5707963267948966,0]},{"text":"A","type":"button","uuid":"67ce1bab-b5cb-4431-ab3b-9755fa91a4ed","color":"red","scale":[0.5,0.5,0.5],"script":"","soundId":"2","version":"5.51.4","position":[2.25,0.75,1.5],"rotation":[0,1.5707963267948966,0]},{"url":"","type":"cube","uuid":"68da36c1-323d-4a02-beb8-fe4a5413ca3c","scale":[0.5,0.5,0.5],"version":"5.51.4","position":[-4.75,1.25,-4.75],"rotation":[0,1.5707963267948966,0]},{"url":"https://opensea.io/assets/0x60f80121c31a0d46b5279700f9df786054aa5ee5/487495","type":"nft-image","uuid":"5f4d8f63-f9d3-4915-b3da-a379e20597e4","scale":[1,1,0],"hasGui":true,"version":"5.51.4","hasFrame":true,"position":[-2.5,1.5,-4.25],"rotation":[0,0,0],"hasGuiResizable":false},{"url":"https://opensea.io/assets/0x60f80121c31a0d46b5279700f9df786054aa5ee5/487495","type":"nft-image","uuid":"cfc2190f-734c-48a6-adc9-6a86c4614ad7","scale":[1,1,0],"hasGui":true,"version":"5.51.4","hasFrame":true,"position":[-2.75,1.75,-4.25],"rotation":[0,0,0],"hasGuiResizable":false},{"url":"","type":"nft-image","uuid":"56e06561-b1e1-49fe-8981-16477b61688d","scale":[1,1,0],"version":"5.51.4","position":[0.75,0.75,0.75],"rotation":[0,1.5707963267948966,0]},{"url":"","type":"cube","uuid":"f88f7afc-5b4b-485d-bce0-b642537dc971","scale":[0.5,0.5,0.5],"version":"5.51.4","position":[-3.25,1.25,-4.75],"rotation":[0,3.141592653589793,0]},{"url":"","type":"cube","uuid":"56d831fc-e684-41a4-b369-ae6b4b84a468","scale":[0.5,0.5,0.5],"version":"5.51.4","position":[-2.75,1.25,-4.75],"rotation":[0,3.141592653589793,0]},{"url":"","type":"cube","uuid":"02077a4f-2b54-40aa-8ce0-ae59e5a524a1","scale":[0.5,0.5,0.5],"version":"5.51.4","position":[4,0.75,0.25],"rotation":[0,1.5707963267948966,0]},{"type":"vid-screen","uuid":"54250545-b8cb-49be-ba35-2ce69f346186","scale":[1,1,0],"version":"5.56.0","position":[6.75,0.75,3],"rotation":[0,1.5707963267948966,0]},{"url":"","type":"cube","uuid":"a35cc876-75c3-44da-830e-564b7be0e13e","scale":[0.5,0.5,0.5],"version":"5.56.0","position":[7,0.75,1.5],"rotation":[0,1.5707963267948966,0]},{"url":"","type":"cube","uuid":"49832a84-4cc5-42a2-9dbb-68bcd1e4fe32","scale":[0.5,0.5,0.5],"version":"5.51.4","position":[-1,0.75,0],"rotation":[0,1.5707963267948966,0]},{"url":"","type":"cube","uuid":"8e964233-6bf5-43a7-9221-deb37925c119","scale":[0.5,0.5,0.5],"version":"5.51.4","position":[-2.5,1.5,-4.5],"rotation":[0,3.141592653589793,0]},{"url":"https://opensea.io/assets/0xb2d6fb1dc231f97f8cc89467b52f7c4f78484044/41843669118736218426464870507024340812464508979130095109650746756000635288660","type":"nft-image","uuid":"0125274e-6fe9-4e73-8927-470a938e89b2","scale":[1,1,0],"hasGui":true,"version":"5.51.4","hasFrame":true,"position":[-1.25,1,-0.25],"rotation":[0,1.5707963267948966,0],"hasGuiResizable":false},{"url":"","type":"cube","uuid":"d4c980ca-bd85-467b-b608-a8cdd0858bce","scale":[0.5,0.5,0.5],"version":"5.51.4","position":[-4,1.25,-4.75],"rotation":[0,1.5707963267948966,0]},{"url":"https://www.youtube.com/watch?v=MwtVkPKx3RA","loop":true,"type":"youtube","uuid":"e9978ccf-1349-4fb8-a22d-b846ee5fb49f","scale":[2,1,0],"script":"","volume":0.7,"version":"5.56.0","autoplay":true,"inverted":false,"position":[6.25,0.75,-2.25],"rotation":[0,1.5707963267948966,0],"screenRatio":"169","rolloffFactor":1.2},{"url":"https://www.cryptovoxels.com/play?coords=E@686E,662S","type":"cube","uuid":"c4812a38-6831-4912-aa52-ea545a4c3e1a","color":"#8d2c45","scale":[0.5,0.5,0.5],"script":"","version":"5.51.4","position":[5,1,-1.25],"rotation":[0,1.5707963267948966,0]}]},"settings":{"sandbox":false,"hosted_scripts":false},"island":"Poneke","kind":"plot","minted":true}}