{"success":true,"parcel":{"id":2878,"hash":"8315f2834a6cc21520fb1536b12581bbfabb500b","features":[{"id":"[coping]","url":"https://media-crvox.sfo2.digitaloceanspaces.com/0xdA2fB270dc5fCE93669620b743ff432927f25dBA/1623330228943-0c658c0f-3c90-4059-932b-48312300f39c.vox","type":"vox-model","uuid":"579c11b7-64b3-4679-b0e5-d48725a6fa36","flipX":true,"scale":[27.5,1.7,1.3],"script":"","version":"6.7.2","position":[-1.95,5.75,6.5],"rotation":[0,0,0],"animation":{"keyframes":[]},"collidable":true},{"id":"[coping]","url":"https://media-crvox.sfo2.digitaloceanspaces.com/0xdA2fB270dc5fCE93669620b743ff432927f25dBA/1623330228943-0c658c0f-3c90-4059-932b-48312300f39c.vox","type":"vox-model","uuid":"3ebc5499-a231-4324-83f5-8e73e75af18c","flipX":true,"scale":[29.96,1.7,1.3],"script":"","version":"6.7.2","position":[-5.48,5.75,2.63],"rotation":[0,1.57,0],"animation":{"keyframes":[]},"collidable":true},{"id":"[FloorTile]","url":"https://i.pinimg.com/originals/68/9a/e3/689ae3f9914ea92308ca3f4ac8ec5438.jpg","type":"image","uuid":"6f728563-5a5b-49a8-b36c-959ada8ac2f1","scale":[11,12,0],"script":"","uScale":"10","vScale":"10","stretch":false,"version":"8.8.1","position":[0.2,0.76,0.25],"rotation":[1.57,0,0],"animation":{"keyframes":[]},"blendMode":"Multiply","transparent":false,"updateDaily":false},{"id":"[AvastarsHat]","url":"https://www.dropbox.com/s/0mi11o4ick1q3rn/AvastarsHat_Rare_02.vox?dl=0","type":"vox-model","uuid":"7391f1d8-ee04-4488-ad05-73540e41a7ed","flipX":true,"scale":[1.3,1.3,1.3],"version":"8.8.1","position":[-2.15,1.45,3.25],"rotation":[0,3.14,0],"animation":{"keyframes":[{"frame":0,"value":[0,0,0]},{"frame":60,"value":[0,0.1,0]},{"frame":120,"value":[0,0,0]}],"destination":"position"}},{"id":"[speakerLight]","type":"lantern","uuid":"143735c2-4f71-45ad-8c8e-bc4b2aabaa1a","color":"#dff4ff","scale":[0.1,8.2,3],"version":"6.7.2","position":[5.75,2.75,3.48],"rotation":[0,0,0],"strength":50},{"id":"[speakerLight]","type":"lantern","uuid":"d0da7fae-5370-4d6a-bfd0-5373fb639947","color":"#dff4ff","scale":[0.1,8.2,3.1],"version":"6.7.2","position":[5.72,2.75,-3.43],"rotation":[0,0,0],"strength":50},{"id":"[VLightOff]","url":"https://www.dropbox.com/s/55mbimt0g92wbem/VLight_off.png?dl=0","type":"image","uuid":"3a617ec0-d489-478d-ae38-829ff0688823","scale":[1,1,0],"script":"","uScale":1,"vScale":1,"stretch":false,"version":"6.7.7","position":[6.05,4.75,-7.1],"rotation":[0,1.5707963267948966,0],"animation":{"keyframes":[]},"blendMode":"Combine","transparent":"AlphaBlend","updateDaily":false},{"id":"[HLightOff]","url":"https://www.dropbox.com/s/wy3ykidpjsen724/HLight_off.png?dl=0","type":"image","uuid":"0144b3ee-9d20-4942-8150-b4fc8c4a9297","scale":[1,1,0],"script":"","uScale":1,"vScale":1,"stretch":false,"version":"6.7.7","position":[6.05,5.76,-7.1],"rotation":[0,1.5707963267948966,0],"animation":{"keyframes":[]},"blendMode":"Combine","transparent":"AlphaBlend","updateDaily":false},{"id":"[YLightOff]","url":"https://www.dropbox.com/s/tdosqnbxmsslj8r/YLight_off.png?dl=0","type":"image","uuid":"d7d173e2-ff68-45c3-b1d7-9c5b53e1ff4f","scale":[1,1,0],"script":"","uScale":1,"vScale":1,"stretch":false,"version":"6.7.7","position":[5.97,3.8,-7.1],"rotation":[0,1.5707963267948966,0],"animation":{"keyframes":[]},"blendMode":"Combine","transparent":"AlphaBlend","updateDaily":false},{"id":"[coping]","url":"https://media-crvox.sfo2.digitaloceanspaces.com/0xdA2fB270dc5fCE93669620b743ff432927f25dBA/1623330228943-0c658c0f-3c90-4059-932b-48312300f39c.vox","type":"vox-model","uuid":"1a2f47b1-7dd6-4877-add9-6e264be323fb","flipX":true,"scale":[30.1,1.7,1.3],"script":"","version":"6.7.2","position":[6.01,5.75,2.65],"rotation":[0,1.57,0],"animation":{"keyframes":[]},"collidable":true},{"id":"[speakerWoofer]","url":"https://media-crvox.sfo2.digitaloceanspaces.com/0xdA2fB270dc5fCE93669620b743ff432927f25dBA/1623325066158-d1765484-9729-4093-9f66-685a1b6d8ee7.vox","type":"vox-model","uuid":"74661b27-f267-49ba-a9fd-ff6a48a52956","flipX":true,"scale":[1.9,1.9,1.9],"script":"","version":"6.7.2","position":[4.66,2.45,3.35],"rotation":[0,-1.57,0],"animation":{"keyframes":[{"frame":0,"value":[1.8,1.8,1.2]},{"frame":4,"value":[2,1.8,1.75]},{"frame":8,"value":[1.8,1.8,1.2]}],"destination":"scaling"},"cubescale":false},{"url":"https://www.dropbox.com/s/bb58az6vqkihn9g/StLouis-Motowall_alpha.png?dl=0","type":"image","uuid":"93f90125-253b-4a12-b6bb-f5002ec40bec","scale":[4.65,1.5,0],"script":"","uScale":1,"vScale":1,"stretch":true,"version":"7.5.0","position":[0.5,5,-5.75],"rotation":[0,3.141592653589793,0],"animation":{"keyframes":[]},"blendMode":"Combine","transparent":"AlphaBlend","updateDaily":false},{"url":"https://www.dropbox.com/s/2bpxturk9w0l174/HVYLightsAnim.gif?dl=0","type":"image","uuid":"c41c77d6-f954-427a-a016-9fcb94feba85","scale":[1.03,3,0],"script":"","uScale":1,"vScale":1,"stretch":false,"version":"6.7.7","position":[6.06,4.78,-7.1],"rotation":[0,1.5707963267948966,0],"animation":{"keyframes":[]},"blendMode":"Combine","transparent":"AlphaTest","updateDaily":false},{"id":"[speakerWoofer]","url":"https://media-crvox.sfo2.digitaloceanspaces.com/0xdA2fB270dc5fCE93669620b743ff432927f25dBA/1623325066158-d1765484-9729-4093-9f66-685a1b6d8ee7.vox","type":"vox-model","uuid":"49666dad-68b1-498e-b3f6-0e16e05cdca9","flipX":true,"scale":[1.9,1.9,1.9],"script":"","version":"6.7.2","position":[4.66,1.05,3.35],"rotation":[0,-1.57,0],"animation":{"keyframes":[{"frame":0,"value":[1.8,1.8,1.2]},{"frame":4,"value":[2,1.8,1.75]},{"frame":8,"value":[1.8,1.8,1.2]}],"destination":"scaling"},"cubescale":false},{"url":"https://www.dropbox.com/s/2bpxturk9w0l174/HVYLightsAnim.gif?dl=0","type":"image","uuid":"4118b7ed-1372-4335-92d1-6c94a3c15741","scale":[1.03,3,0],"script":"","uScale":"1","vScale":1,"stretch":false,"version":"6.7.7","position":[5.95,4.78,-7.1],"rotation":[0,1.5707963267948966,0],"animation":{"keyframes":[]},"blendMode":"Combine","transparent":"AlphaTest","updateDaily":false},{"id":"[YLightOff]","url":"https://www.dropbox.com/s/tdosqnbxmsslj8r/YLight_off.png?dl=0","type":"image","uuid":"c1e12561-7bff-42b8-a512-acc3a82ff191","scale":[1,1,0],"script":"","uScale":1,"vScale":1,"stretch":false,"version":"6.7.7","position":[6.05,3.8,-7.1],"rotation":[0,1.5707963267948966,0],"animation":{"keyframes":[]},"blendMode":"Combine","transparent":"AlphaBlend","updateDaily":false},{"id":"[speakerWoofer]","url":"https://media-crvox.sfo2.digitaloceanspaces.com/0xdA2fB270dc5fCE93669620b743ff432927f25dBA/1623325066158-d1765484-9729-4093-9f66-685a1b6d8ee7.vox","type":"vox-model","uuid":"d4a7fc20-7252-467a-a0ed-c6668680d3a8","flipX":true,"scale":[1.2,1.2,1.2],"script":"","version":"6.7.2","position":[4.68,3.8,-3.6],"rotation":[0,4.71,0],"animation":{"keyframes":[{"frame":0,"value":[1.2,1.2,1.2]},{"frame":4,"value":[1.4,1.2,1.25]},{"frame":8,"value":[1.2,1.2,1.2]}],"destination":"scaling"},"cubescale":false},{"id":"[speakerWoofer]","url":"https://media-crvox.sfo2.digitaloceanspaces.com/0xdA2fB270dc5fCE93669620b743ff432927f25dBA/1623325066158-d1765484-9729-4093-9f66-685a1b6d8ee7.vox","type":"vox-model","uuid":"a935c290-2a9f-47c8-9d9b-3c82c57b5198","flipX":true,"scale":[1.9,1.9,1.9],"script":"","version":"6.7.2","position":[4.66,2.45,-3.65],"rotation":[0,-1.57,0],"animation":{"keyframes":[{"frame":0,"value":[1.8,1.8,1.2]},{"frame":4,"value":[2,1.8,1.75]},{"frame":8,"value":[1.8,1.8,1.2]}],"destination":"scaling"},"cubescale":false},{"id":"[speakerWoofer]","url":"https://media-crvox.sfo2.digitaloceanspaces.com/0xdA2fB270dc5fCE93669620b743ff432927f25dBA/1623325066158-d1765484-9729-4093-9f66-685a1b6d8ee7.vox","type":"vox-model","uuid":"c0117d3b-a079-471f-814b-b596def70f22","flipX":true,"scale":[1.9,1.9,1.9],"script":"","version":"6.7.2","position":[4.66,1.05,-3.65],"rotation":[0,-1.57,0],"animation":{"keyframes":[{"frame":0,"value":[1.8,1.8,1.2]},{"frame":4,"value":[2,1.8,1.75]},{"frame":8,"value":[1.8,1.8,1.2]}],"destination":"scaling"},"cubescale":false},{"id":"[coping]","url":"https://media-crvox.sfo2.digitaloceanspaces.com/0xdA2fB270dc5fCE93669620b743ff432927f25dBA/1623331462055-d6f98882-b10d-4736-a4b1-a672800a3dc0.vox","type":"vox-model","uuid":"ab18740c-fa07-4349-b094-681aa826cf9d","flipX":true,"scale":[1.3,1.7,1.3],"script":"","version":"6.7.2","position":[5.89,5.75,6.5],"rotation":[0,0,0],"animation":{"keyframes":[]},"cubescale":false,"collidable":true},{"id":"[coping]","url":"https://media-crvox.sfo2.digitaloceanspaces.com/0xdA2fB270dc5fCE93669620b743ff432927f25dBA/1623331462055-d6f98882-b10d-4736-a4b1-a672800a3dc0.vox","type":"vox-model","uuid":"7eee370b-7d9a-4a28-b926-d7fce5c9a222","flipX":true,"scale":[1.3,1.7,1.3],"script":"","version":"6.7.2","position":[-5.51,5.75,6.38],"rotation":[0,4.71,0],"animation":{"keyframes":[]},"cubescale":false,"collidable":true},{"id":"[speakerWoofer]","url":"https://media-crvox.sfo2.digitaloceanspaces.com/0xdA2fB270dc5fCE93669620b743ff432927f25dBA/1623325066158-d1765484-9729-4093-9f66-685a1b6d8ee7.vox","type":"vox-model","uuid":"ca4e9dce-9b4b-41ef-9ebb-2eeae0c9d6ac","flipX":true,"scale":[1.2,1.2,1.2],"script":"","version":"6.7.2","position":[4.68,3.8,3.41],"rotation":[0,4.71,0],"animation":{"keyframes":[{"frame":0,"value":[1.2,1.2,1.2]},{"frame":4,"value":[1.4,1.2,1.25]},{"frame":8,"value":[1.2,1.2,1.2]}],"destination":"scaling"},"cubescale":false},{"id":"[interiorLight]","type":"lantern","uuid":"9a0531e6-dba9-43d5-8d5d-883e46973df6","color":"#ff00aa","scale":[22.7,0.1,0.1],"version":"6.11.2","position":[0.1,4.22,6.24],"rotation":[0,0,0],"strength":"20"},{"id":"[wallMural - moscow]","url":"https://www.dropbox.com/s/9zanqtpwfega5wo/moscow-mural-heavy_alpha.png?dl=0","link":"https://www.heavy.io/moscow","type":"image","uuid":"acc6c640-00ea-4b66-9e53-3fa1ea59df0f","scale":[2.7,1.5,0],"script":"","uScale":"1","vScale":"1","stretch":true,"version":"7.5.0","position":[-5.25,5,-0.6],"rotation":[0,4.71238898038469,0],"animation":{"keyframes":[]},"blendMode":"Combine","transparent":"AlphaBlend","updateDaily":false},{"id":"[wallMural - SFDW]","url":"https://www.dropbox.com/s/k6qgmvgh92pzpue/SFDW_alpha.png?dl=0","link":"https://www.heavy.io/parabola","type":"image","uuid":"dd142690-84bb-479f-894b-523885659f99","scale":[5.1,1.53,0],"script":"","uScale":"1","vScale":"1","stretch":true,"version":"7.0.0","position":[-5.25,5,3.45],"rotation":[0,4.71238898038469,0],"animation":{"keyframes":[]},"blendMode":"Combine","transparent":"AlphaBlend","updateDaily":false},{"id":"[wallMural - geneva]","url":"https://www.dropbox.com/s/lkc3yjjokhnmykm/geneva_alpha.png?dl=0","link":"https://www.heavy.io/geneva","type":"image","uuid":"866a7877-cd60-40f8-870f-2cfb15114d5b","scale":[3.3,1.5,0],"script":"","uScale":"1","vScale":"1","stretch":true,"version":"7.5.0","position":[-5.25,5,-3.8],"rotation":[0,4.71238898038469,0],"animation":{"keyframes":[]},"blendMode":"Combine","transparent":"AlphaBlend","updateDaily":false},{"id":"[retailSluts-Lights]","url":"https://www.dropbox.com/s/r7uk2ti1d6xjdkf/Retail%20SLUT_lightsonly.png?dl=0","type":"image","uuid":"34f689dc-081c-4391-a030-973cc053b27b","scale":[6.83,2.5,0],"script":"","uScale":1,"vScale":1,"stretch":true,"version":"6.11.2","position":[-5.8,4.48,0.25],"rotation":[0,1.57,0],"animation":{"keyframes":[{"frame":0,"value":[0,0,0]},{"frame":1,"value":[0.03,0,0]},{"frame":4,"value":[0,0,0]}],"destination":""},"blendMode":"Combine","transparent":"AlphaBlend","updateDaily":false},{"id":"[coping]","url":"https://media-crvox.sfo2.digitaloceanspaces.com/0xdA2fB270dc5fCE93669620b743ff432927f25dBA/1623330228943-0c658c0f-3c90-4059-932b-48312300f39c.vox","type":"vox-model","uuid":"0a129835-16c3-4e2f-9ec2-8863e8ca8158","flipX":true,"scale":[27.5,1.7,1.3],"script":"","version":"7.5.0","position":[-1.95,5.75,-6],"rotation":[0,0,0],"animation":{"keyframes":[]},"collidable":true},{"id":"[coping]","url":"https://media-crvox.sfo2.digitaloceanspaces.com/0xdA2fB270dc5fCE93669620b743ff432927f25dBA/1623331462055-d6f98882-b10d-4736-a4b1-a672800a3dc0.vox","type":"vox-model","uuid":"34e2a472-bda0-4abc-83cf-14472adc2351","flipX":true,"scale":[1.3,1.7,1.3],"script":"","version":"7.5.0","position":[6.02,5.75,-5.91],"rotation":[0,1.57,0],"animation":{"keyframes":[]},"cubescale":false,"collidable":true},{"id":"[coping]","url":"https://media-crvox.sfo2.digitaloceanspaces.com/0xdA2fB270dc5fCE93669620b743ff432927f25dBA/1623331462055-d6f98882-b10d-4736-a4b1-a672800a3dc0.vox","type":"vox-model","uuid":"714271ed-8c97-4af2-b313-6dfb781dc8a9","flipX":true,"scale":[1.3,1.7,1.3],"script":"","version":"7.5.0","position":[-5.38,5.75,-6.02],"rotation":[0,3.14,0],"animation":{"keyframes":[]},"cubescale":false,"collidable":true},{"id":"[FireHat]","url":"https://www.dropbox.com/s/f7rbfuhfzcj0983/cn_FireHat_Uncommon_1559redhot.vox?dl=0","type":"vox-model","uuid":"3a3fbc79-0961-4aae-9e3b-1b69f41a4b95","flipX":true,"scale":[1.3,1.3,1.3],"version":"8.8.1","position":[-2.15,1.5,-3.25],"rotation":[0,3.14,0],"animation":{"keyframes":[{"frame":0,"value":[0,0,0]},{"frame":60,"value":[0,0.1,0]},{"frame":120,"value":[0,0,0]}],"destination":"position"}},{"id":"[PunksHat]","url":"https://www.dropbox.com/s/kr4dfqjmwgd2ovr/cn_PunksHat_Legendary_8870.vox?dl=0","type":"vox-model","uuid":"43cc398e-949b-4562-ab51-c01a4da4ac92","flipX":true,"scale":[1.3,1.3,1.3],"version":"8.8.1","position":[1.35,1.45,-3.2],"rotation":[0,3.14,0],"animation":{"keyframes":[{"frame":0,"value":[0,0,0]},{"frame":60,"value":[0,0.1,0]},{"frame":120,"value":[0,0,0]}],"destination":"position"}},{"id":"[ApesHat]","url":"https://www.dropbox.com/s/nx4ieger9owv7a0/cn_ApesHat_Epic_skull.vox?dl=0","type":"vox-model","uuid":"e5056d79-b82f-4e76-89b3-1e4bf640e0df","flipX":true,"scale":[1.3,1.3,1.3],"version":"8.8.1","position":[1.35,1.55,3.25],"rotation":[0,3.14,0],"animation":{"keyframes":[{"frame":0,"value":[0,0,0]},{"frame":60,"value":[0,0.1,0]},{"frame":120,"value":[0,0,0]}],"destination":"position"}},{"url":"https://www.dropbox.com/s/0dyi0pj6toddxvd/Austin_alpha.png?dl=0","type":"image","uuid":"4eefcfbd-b278-46d7-9e91-f1ece4a64e7a","scale":[3,1.48,0],"script":"","uScale":1,"vScale":1,"stretch":true,"version":"7.5.0","position":[-3.5,5,-5.75],"rotation":[0,3.141592653589793,0],"animation":{"keyframes":[]},"blendMode":"Combine","transparent":"AlphaBlend","updateDaily":false},{"url":"https://www.dropbox.com/s/md803u45kh8l4si/SanDiego_Alpha.png?dl=0","type":"image","uuid":"89394306-6c46-4bbe-9ad0-07f806baecac","scale":[8.4,1.4,0],"script":"","uScale":1,"vScale":1,"stretch":true,"version":"7.5.0","position":[-0.8,5,6.25],"rotation":[0,0,0],"animation":{"keyframes":[]},"blendMode":"Combine","transparent":"AlphaBlend","updateDaily":false},{"id":"[interiorLight]","type":"lantern","uuid":"d86d89e4-69f7-4510-9ff8-2d6b89f88bc6","color":"#ff00aa","scale":[22.7,0.1,0.1],"version":"7.0.0","position":[0.4,4.22,-5.75],"rotation":[0,0,0],"strength":"20"},{"id":"[AudioPlayer]","url":"https://www.dropbox.com/s/ggg8hr7lbqmab1k/Hvy%20WC%200_2.wav?dl=0","loop":true,"type":"audio","uuid":"a85399cc-d250-46e5-ab79-39179c40bd97","scale":[1.4,0.35,0],"script":"","volume":0.78,"version":"8.8.1","autoplay":true,"position":[5.7,3.1,0],"rotation":[0,1.57,0],"rolloffFactor":0.8},{"url":"https://gateway.pinata.cloud/ipfs/QmP8NwUPU5Ngxy38h8mbpTqZMTvPez5kQs5iEUEnKH7UYs/ChadMannequin-15327.vox","type":"megavox","uuid":"da85084f-0a8f-4aae-86b4-db38ac3b7436","flipX":true,"scale":[1.4,1.4,1.4],"script":"","version":"6.8.3","position":[3.5,0.75,5],"rotation":[0,3.84,0],"animation":{"keyframes":[]},"collidable":true},{"url":"https://media-crvox.sfo2.digitaloceanspaces.com/0xda2fb270dc5fce93669620b743ff432927f25dba/1624274454333-54c7ed21-9c0b-4df4-9c8c-6832f5810bcd.vox","type":"vox-model","uuid":"4d15714d-742a-4334-b249-5d7fb67a7146","flipX":true,"scale":[4.2,5,1],"script":"","version":"6.7.7","position":[6,3.2,-7.44],"rotation":[0,-1.57,0],"animation":{"keyframes":[]}},{"id":"[featureWall]","url":"https://media-crvox.sfo2.digitaloceanspaces.com/0xdA2fB270dc5fCE93669620b743ff432927f25dBA/1623411712162-56f47003-75d2-423b-a00e-98e66b47e993.png","type":"image","uuid":"c8014c69-1861-4c91-93f5-cff4e764d69b","scale":[12,4.4,0],"script":"","uScale":"3","vScale":1,"stretch":false,"version":"6.7.2","position":[5.74,2.95,0.25],"rotation":[0,1.57,0],"animation":{"keyframes":[]},"blendMode":"Screen","transparent":false,"updateDaily":false},{"id":"[HLightOff]","url":"https://www.dropbox.com/s/wy3ykidpjsen724/HLight_off.png?dl=0","type":"image","uuid":"6bb222ce-e0c4-4e3a-89fd-9a8f1f59719d","scale":[1,1,0],"script":"","uScale":1,"vScale":1,"stretch":false,"version":"6.7.7","position":[5.97,5.75,-7.1],"rotation":[0,1.5707963267948966,0],"animation":{"keyframes":[]},"blendMode":"Combine","transparent":"AlphaBlend","updateDaily":false},{"id":"[VLightOFF]","url":"https://www.dropbox.com/s/55mbimt0g92wbem/VLight_off.png?dl=0","type":"image","uuid":"7b099913-cc81-43e1-ad2a-eac68890559b","scale":[1,1,0],"script":"","uScale":1,"vScale":1,"stretch":false,"version":"6.7.7","position":[5.97,4.75,-7.1],"rotation":[0,1.5707963267948966,0],"animation":{"keyframes":[],"destination":""},"blendMode":"Combine","transparent":"AlphaBlend","updateDaily":false},{"id":"[interiorLight]","type":"lantern","uuid":"36139335-c6b4-4230-933c-3babcacbf6bc","color":"#ff00aa","scale":[0.1,0.1,24],"version":"6.7.2","position":[-5.25,4.22,0.48],"rotation":[0,0,0],"strength":"20"},{"type":"spawn-point","uuid":"7c33be46-cd56-4bf1-979e-b262f15792f0","scale":[1,1,1],"version":"6.6.0","position":[-2.25,0.75,0],"rotation":[0,1.57,0]},{"id":"[exteriorLight]","type":"lantern","uuid":"b4436aa8-5c41-4c3a-9a81-11470a9355c4","color":"#ffffff","scale":[0.3,0.05,24],"version":"6.7.3","position":[-5.8,5.72,0.49],"rotation":[0,0,0],"strength":"100"},{"id":"[banner]","url":"https://www.dropbox.com/s/zz16xo5pb5sbg8p/Retail%20SLUT02_lightsOFF_flippedOpacities.png?dl=0","type":"image","uuid":"da7bef4c-37e7-42e3-8691-c87e11426720","scale":[6.83,2.5,0],"script":"","uScale":1,"vScale":1,"stretch":true,"version":"6.11.2","position":[-5.76,4.48,0.25],"rotation":[0,1.57,0],"animation":{"keyframes":[]},"blendMode":"Multiply","transparent":false,"updateDaily":false},{"id":"[homePage]","url":"https://www.dropbox.com/s/yhzvioc29i259of/AVhome.png?dl=0","link":"https://www.heavy.io/","type":"image","uuid":"5ecd8e08-3287-4ad3-994e-e37df34d2396","scale":[1,1,0],"script":"","uScale":1,"vScale":1,"stretch":true,"version":"6.7.2","position":[-5.25,3.65,5.4],"rotation":[0,-1.57,0],"animation":{"keyframes":[]},"blendMode":"Combine","transparent":"AlphaBlend","updateDaily":false},{"id":"[linkedIn]","url":"https://www.dropbox.com/s/3o1ao3w4o7brk22/linkedIn.png?dl=0","link":"https://www.linkedin.com/company/heavyio/mycompany/","type":"image","uuid":"97a213ea-131d-46af-9c47-f9c7cb9b24b8","scale":[1,1,0],"script":"","uScale":1,"vScale":1,"stretch":true,"version":"6.7.2","position":[-5.24,3.65,4.2],"rotation":[0,-1.57,0],"animation":{"keyframes":[]},"blendMode":"Combine","transparent":"AlphaBlend","updateDaily":false},{"id":"[twitter]","url":"https://www.dropbox.com/s/au0qb55ey3reqyj/twitter.png?dl=0","link":"https://twitter.com/heavyprojects?lang=en","type":"image","uuid":"aed9d7f1-b9a7-4453-b016-1a9c1294e0ef","scale":[1,1,0],"script":"","uScale":1,"vScale":1,"stretch":true,"version":"6.7.2","position":[-5.24,3.65,3.1],"rotation":[0,-1.57,0],"animation":{"keyframes":[]},"blendMode":"Combine","transparent":"AlphaBlend","updateDaily":false},{"id":"[exitSign]","url":"https://www.dropbox.com/s/jv4nnwbj8drvg3y/exitLine.png?dl=0","type":"image","uuid":"9e2cc763-581c-49fa-b570-08ab27afefa8","scale":[6.5,1,0],"script":"","uScale":1,"vScale":1,"stretch":true,"version":"6.7.2","position":[-5.24,3.7,-0.85],"rotation":[0,-1.57,0],"animation":{"keyframes":[]},"blendMode":"Combine","transparent":"AlphaBlend","updateDaily":false},{"id":"[BigHat]","url":"https://media-crvox.sfo2.digitaloceanspaces.com/0xdA2fB270dc5fCE93669620b743ff432927f25dBA/1624031647537-ecd5fc27-52e1-47ad-b0a2-22f20c5f0b26.vox","type":"vox-model","uuid":"fd190bab-e76b-4e12-b7a5-962057e2372b","flipX":true,"scale":[7,7,7],"script":"","version":"6.8.3","position":[-5.2,6.05,6.3],"rotation":[0,0.79,0.35],"animation":{"keyframes":[]},"collidable":true},{"id":"[spinningH]","url":"https://media-crvox.sfo2.digitaloceanspaces.com/0xdA2fB270dc5fCE93669620b743ff432927f25dBA/1623684271349-131ac263-9f91-45cc-96ba-82d89f0f3f6d.vox","type":"vox-model","uuid":"35b1eb08-ef67-413b-b59a-0e471d2f6560","flipX":true,"scale":[1,1,1],"script":"","version":"6.7.2","position":[6,5.9,-6],"rotation":[0,-3.141592653589793,0],"animation":{"keyframes":[{"frame":0,"value":[0,0,0]},{"frame":80,"value":[0,6.28319,0]}],"destination":"rotation"}},{"id":"[spinningH]","url":"https://media-crvox.sfo2.digitaloceanspaces.com/0xdA2fB270dc5fCE93669620b743ff432927f25dBA/1623684271349-131ac263-9f91-45cc-96ba-82d89f0f3f6d.vox","type":"vox-model","uuid":"7bdcfeb0-b2e1-40db-bc5f-63b1e12d7a27","flipX":true,"scale":[1,1,1],"script":"","version":"6.7.2","position":[6,5.9,6.5],"rotation":[0,-3.141592653589793,0],"animation":{"keyframes":[{"frame":0,"value":[0,0,0]},{"frame":80,"value":[0,6.28319,0]}],"destination":"rotation"}},{"id":"[spinningH]","url":"https://media-crvox.sfo2.digitaloceanspaces.com/0xdA2fB270dc5fCE93669620b743ff432927f25dBA/1623684271349-131ac263-9f91-45cc-96ba-82d89f0f3f6d.vox","type":"vox-model","uuid":"f0b6f271-a42c-437c-82c4-35abcf88e946","flipX":true,"scale":[1,1,1],"script":"","version":"6.7.2","position":[-5.5,5.9,6.5],"rotation":[0,-3.141592653589793,0],"animation":{"keyframes":[{"frame":0,"value":[0,0,0]},{"frame":80,"value":[0,6.28319,0]}],"destination":"rotation"}},{"id":"[spinningH]","url":"https://media-crvox.sfo2.digitaloceanspaces.com/0xdA2fB270dc5fCE93669620b743ff432927f25dBA/1623684271349-131ac263-9f91-45cc-96ba-82d89f0f3f6d.vox","type":"vox-model","uuid":"cb7c1857-bc8a-4474-b7a4-d5c4c60d3540","flipX":true,"scale":[1,1,1],"script":"","version":"6.7.2","position":[-5.5,5.9,-6],"rotation":[0,-3.141592653589793,0],"animation":{"keyframes":[{"frame":0,"value":[0,0,0]},{"frame":80,"value":[0,6.28319,0]}],"destination":"rotation"}}],"settings":{"sandbox":false,"hosted_scripts":true},"voxels":"eJzt10EOgjAQheECYc+depQewCv0rl5EXSiSCJkZtXl9vM7GpPljG75gHOoQmNk5jyI510zYTM7ha/zWxuT/nsH9dFKa6Bp/xdfE3m7yFmmQHcgbtp1Ig+xA3rDtRBpkB/KGbSfSIDvg9bbUZeec253324z3+by2O9821iVv8vaLxrrkrR9v9rOxNcgO5A3bTqRBdiBv2HYiDbKDVs2Y5K1Vg+xA7zdsO5EG2QGvN/0/PXMjb/LG7c1+NrYG2cE5vJX6mL2zeW+D3iA7OIe347OxNcgO5A3bTqRBdiBv2HYiDbKD1t6KvP29QXbA6i3Xa80759zurbdhaZ4VcmNfffye5poDz/Soyd00q4NWDYe3mNFimsvr02xuippumhuvYKqO","owner":"0x5C57abD3548b87Ef9bAbEa37ed3abD51fad523a3","lightmap_status":"Baked","parcel_users":[{"wallet":"0xda2fb270dc5fce93669620b743ff432927f25dba","role":"contributor"},{"wallet":"0xef49f13ab6e392f5ae4f2dbbeb619b128e0ad37b","role":"contributor"}],"description":"HEAVY is an award-winning Augmented Reality studio doing NFT drops in collaboration with musicians and fine artists.","name":null,"label":"","address":"8 Hide Branch","suburb":"Modville","island":"Origin City","x1":379,"y1":0,"z1":424,"x2":391,"y2":6,"z2":437,"tileset":"/uploads/atlas/b66918eb69c2ca59ac311bd5ca102aebdf4b32d0.png","brightness":2.4,"palette":["#ffffff","#cdcdcd","#111111","#fb4bfb","#fc83fc","#00ff73","#b967ff","#616161"],"is_common":false,"visible":true,"kind":"plot"}}